keyring_gitlab_pypi-1.1.dist-info/licenses/LICENSE
keyrings/gitlab_pypi/__init__.py
keyrings/gitlab_pypi/py.typed
keyring_gitlab_pypi-1.1.dist-info/METADATA
keyring_gitlab_pypi-1.1.dist-info/WHEEL
keyring_gitlab_pypi-1.1.dist-info/entry_points.txt
keyring_gitlab_pypi-1.1.dist-info/top_level.txt
keyring_gitlab_pypi-1.1.dist-info/RECORD
