Metadata-Version: 2.4
Name: keyring-gitlab-pypi
Version: 1.1
Summary: keyring backend for GitLab package indexes
Author-email: Frazer McLean <frazer@frazermclean.co.uk>
License-Expression: MIT
Project-URL: Repository, https://github.com/RazerM/keyring-gitlab-pypi
Classifier: Development Status :: 5 - Production/Stable
Classifier: Programming Language :: Python :: 3 :: Only
Classifier: Programming Language :: Python :: 3.9
Classifier: Programming Language :: Python :: 3.10
Classifier: Programming Language :: Python :: 3.11
Classifier: Programming Language :: Python :: 3.12
Classifier: Programming Language :: Python :: 3.13
Requires-Python: >=3.9
License-File: LICENSE
Requires-Dist: keyring>=25.6.0
Requires-Dist: platformdirs>=4.3.7
Requires-Dist: tomli>=2.2.1; python_full_version < "3.11"
Requires-Dist: yarl>=1.19.0
Dynamic: license-file
